redflagbpm/BPMService.py
redflagbpm/Logging.py
redflagbpm/MSSQLUtils.py
redflagbpm/PgUtils.py
redflagbpm/Services.py
redflagbpm/__init__.py
redflagbpm-0.0.62.dist-info/licenses/LICENCE
redflagbpm-0.0.62.dist-info/METADATA
redflagbpm-0.0.62.dist-info/WHEEL
redflagbpm-0.0.62.dist-info/top_level.txt
redflagbpm-0.0.62.dist-info/RECORD
