Metadata-Version: 2.4
Name: redflagbpm
Version: 0.0.62
Summary: BPM service extension
Home-page: https://gitlab.com/redflagdev/redflagbpm-python
Author: Germán Dressino
Author-email: gdressino@redflag.dev
Project-URL: Bug Tracker, https://gitlab.com/redflagdev/redflagbpm-python/issues
Classifier: Programming Language :: Python :: 3
Classifier: Operating System :: OS Independent
Requires-Python: >=3.7
License-File: LICENCE
Requires-Dist: vertx-eventbus-client
Dynamic: author
Dynamic: author-email
Dynamic: classifier
Dynamic: description
Dynamic: description-content-type
Dynamic: home-page
Dynamic: license-file
Dynamic: project-url
Dynamic: requires-dist
Dynamic: requires-python
Dynamic: summary
